cflib/__init__.py
cflib/bootloader/__init__.py
cflib/bootloader/boottypes.py
cflib/bootloader/cloader.py
cflib/cpx/__init__.py
cflib/cpx/transports.py
cflib/crazyflie/__init__.py
cflib/crazyflie/appchannel.py
cflib/crazyflie/commander.py
cflib/crazyflie/console.py
cflib/crazyflie/extpos.py
cflib/crazyflie/high_level_commander.py
cflib/crazyflie/link_statistics.py
cflib/crazyflie/localization.py
cflib/crazyflie/log.py
cflib/crazyflie/param.py
cflib/crazyflie/platformservice.py
cflib/crazyflie/swarm.py
cflib/crazyflie/syncCrazyflie.py
cflib/crazyflie/syncLogger.py
cflib/crazyflie/toc.py
cflib/crazyflie/toccache.py
cflib/crazyflie/mem/__init__.py
cflib/crazyflie/mem/deck_memory.py
cflib/crazyflie/mem/i2c_element.py
cflib/crazyflie/mem/led_driver_memory.py
cflib/crazyflie/mem/led_timings_driver_memory.py
cflib/crazyflie/mem/lighthouse_memory.py
cflib/crazyflie/mem/loco_memory.py
cflib/crazyflie/mem/loco_memory_2.py
cflib/crazyflie/mem/memory_element.py
cflib/crazyflie/mem/memory_tester.py
cflib/crazyflie/mem/multiranger_memory.py
cflib/crazyflie/mem/ow_element.py
cflib/crazyflie/mem/paa3905_memory.py
cflib/crazyflie/mem/trajectory_memory.py
cflib/crtp/__init__.py
cflib/crtp/cflinkcppdriver.py
cflib/crtp/crtpdriver.py
cflib/crtp/crtpstack.py
cflib/crtp/exceptions.py
cflib/crtp/pcap.py
cflib/crtp/prrtdriver.py
cflib/crtp/radio_link_statistics.py
cflib/crtp/radiodriver.py
cflib/crtp/serialdriver.py
cflib/crtp/tcpdriver.py
cflib/crtp/udpdriver.py
cflib/crtp/usbdriver.py
cflib/drivers/__init__.py
cflib/drivers/cfusb.py
cflib/drivers/crazyradio.py
cflib/localization/__init__.py
cflib/localization/_ippe.py
cflib/localization/ippe_cf.py
cflib/localization/lighthouse_bs_vector.py
cflib/localization/lighthouse_config_manager.py
cflib/localization/lighthouse_geometry_solver.py
cflib/localization/lighthouse_initial_estimator.py
cflib/localization/lighthouse_sample_matcher.py
cflib/localization/lighthouse_sweep_angle_reader.py
cflib/localization/lighthouse_system_aligner.py
cflib-0.1.29.dist-info/licenses/LICENSE.txt
cflib-0.1.29.dist-info/METADATA
cflib-0.1.29.dist-info/WHEEL
cflib-0.1.29.dist-info/top_level.txt
cflib-0.1.29.dist-info/RECORD
